{
  "cluster_name": "on_off",
  "cluster_id": "0x0006",
  "query_type": "cluster_states",
  "answer": "Based on the provided Matter specification, I will analyze the On/Off cluster (ID: 0x0006) and extract its formal finite state machine (FSM). The output will be in JSON format as specified.\n\n**Cluster Context**\n\n* Cluster ID: 0x0006\n* Cluster Name: On/Off\n* Category: Lighting\n* Description: Basic on/off functionality for devices\n\n**Attributes**\n\n* OnOff: Boolean attribute indicating the device's current state (on or off)\n* GlobalSceneControl: Boolean attribute controlling global scene control\n* OnTime: Integer attribute representing the time spent in the \"On\" state\n* OffWaitTime: Integer attribute representing the time spent in the \"Off\" state\n\n**Commands**\n\n* Off: Command to turn the device off\n* On: Command to turn the device on\n* Toggle: Command to toggle the device's state (on or off)\n\n**Events**\n\n* StateChanged: Event triggered when the device's state changes\n\n**Formal FSM Extraction**\n\nBased on the cluster context, attributes, commands, and events, I will extract the complete state space for the On/Off cluster.\n\n```json\n{\n    \"cluster_id\": \"0x0006\",\n    \"cluster_name\": \"On/Off\",\n    \"fsm_type\": \"cluster_states\",\n    \"states\": [\n        {\n            \"state_id\": \"OFF_STATE\",\n            \"state_name\": \"Device is off\",\n            \"state_type\": \"operational\",\n            \"description\": \"The device is in the 'off' state.\",\n            \"preconditions\": [\"OnOff == false\"],\n            \"invariants\": [\"OnOff == false\", \"GlobalSceneControl == false\"],\n            \"atomic_propositions\": [\"device_is_off\", \"global_scene_control_disabled\"],\n            \"attribute_values\": {\"OnOff\": \"false\"}\n        },\n        {\n            \"state_id\": \"ON_STATE\",\n            \"state_name\": \"Device is on\",\n            \"state_type\": \"operational\",\n            \"description\": \"The device is in the 'on' state.\",\n            \"preconditions\": [\"OnOff == true\"],\n            \"invariants\": [\"OnOff == true\", \"GlobalSceneControl == false\"],\n            \"atomic_propositions\": [\"device_is_on\", \"global_scene_control_disabled\"],\n            \"attribute_values\": {\"OnOff\": \"true\"}\n        },\n        {\n            \"state_id\": \"TOGGLE_TRANSIENT\",\n            \"state_name\": \"Device is in toggle transient state\",\n            \"state_type\": \"transient\",\n            \"description\": \"The device is transitioning between 'on' and 'off' states.\",\n            \"preconditions\": [\"Toggle command received\"],\n            \"invariants\": [\"OnOff == true || OnOff == false\", \"GlobalSceneControl == false\"],\n            \"atomic_propositions\": [\"device_is_toggling\"],\n            \"attribute_values\": {\"OnOff\": \"true\" | \"false\"}\n        },\n        {\n            \"state_id\": \"INITIAL_STATE\",\n            \"state_name\": \"Device initialization state\",\n            \"state_type\": \"initial\",\n            \"description\": \"The device is in its initial state.\",\n            \"preconditions\": [\"Device startup\"],\n            \"invariants\": [\"OnOff == false\", \"GlobalSceneControl == false\"],\n            \"atomic_propositions\": [\"device_is_initializing\"],\n            \"attribute_values\": {\"OnOff\": \"false\"}\n        },\n        {\n            \"state_id\": \"FINAL_STATE\",\n            \"state_name\": \"Device termination state\",\n            \"state_type\": \"final\",\n            \"description\": \"The device is in its final state.\",\n            \"preconditions\": [\"Device shutdown\"],\n            \"invariants\": [\"OnOff == false\", \"GlobalSceneControl == false\"],\n            \"atomic_propositions\": [\"device_is_terminating\"],\n            \"attribute_values\": {\"OnOff\": \"false\"}\n        }\n    ]\n}\n```\n\nThis JSON output represents the complete state space for the On/Off cluster, including operational states (OFF_STATE and ON_STATE), transient states (TOGGLE_TRANSIENT), initial state (INITIAL_STATE), and final state (FINAL_STATE). Each state includes its formal identifier, human-readable name, description, preconditions, invariants, atomic propositions, and attribute values.",
  "timestamp": "D:\\Thesis_Matter_2025\\Codes\\FSM_Generator",
  "thread_id": "on_off_cluster_states"
}